setup.py
zeblonk_probability/Binomialdistribution.py
zeblonk_probability/Gaussiandistribution.py
zeblonk_probability/Generaldistribution.py
zeblonk_probability/__init__.py
zeblonk_probability.egg-info/PKG-INFO
zeblonk_probability.egg-info/SOURCES.txt
zeblonk_probability.egg-info/dependency_links.txt
zeblonk_probability.egg-info/not-zip-safe
zeblonk_probability.egg-info/top_level.txt