Metadata-Version: 1.0
Name: zeblonk-probability
Version: 0.2
Summary: Gaussian and Binomial distributions
Home-page: UNKNOWN
Author: Jason Ho
Author-email: UNKNOWN
License: UNKNOWN
Platform: UNKNOWN
